CHANGES.txt
MANIFEST.in
README.rst
setup.py
repoze/__init__.py
repoze.who.plugins.browserid.egg-info/PKG-INFO
repoze.who.plugins.browserid.egg-info/SOURCES.txt
repoze.who.plugins.browserid.egg-info/dependency_links.txt
repoze.who.plugins.browserid.egg-info/namespace_packages.txt
repoze.who.plugins.browserid.egg-info/not-zip-safe
repoze.who.plugins.browserid.egg-info/requires.txt
repoze.who.plugins.browserid.egg-info/top_level.txt
repoze/who/__init__.py
repoze/who/plugins/__init__.py
repoze/who/plugins/browserid/__init__.py
repoze/who/plugins/browserid/utils.py
repoze/who/plugins/browserid/tests/__init__.py
repoze/who/plugins/browserid/tests/test_plugin.py
repoze/who/plugins/browserid/tests/test_utils.py