Metadata-Version: 1.0
Name: repoze.who.plugins.browserid
Version: 0.2.1
Summary: repoze.who.plugins.browserid
Home-page: https://github.com/mozilla-services/repoze.who.plugins.browserid
Author: Mozilla Services
Author-email: services-dev@mozilla.org
License: UNKNOWN
Keywords: authentication repoze browserid
Platform: UNKNOWN
Classifier: Programming Language :: Python
